cryptoblocks64.py
cryptoblocks64-0.0.4.dist-info/METADATA
cryptoblocks64-0.0.4.dist-info/WHEEL
cryptoblocks64-0.0.4.dist-info/license.txt
cryptoblocks64-0.0.4.dist-info/top_level.txt
cryptoblocks64-0.0.4.dist-info/RECORD
