Metadata-Version: 2.1
Name: cryptoblocks64
Version: 0.0.4
Summary: A collection of common cryptography related functions but in B64 operation format
Home-page: https://github.com/ApratimR/crypto_blocks
Author: Apratim Ray
Author-email: apratimr55@gmail.com
License: UNKNOWN
Platform: UNKNOWN
Classifier: Programming Language :: Python :: 3
Classifier: License :: OSI Approved :: GNU General Public License v3 (GPLv3)
Classifier: Operating System :: OS Independent
Requires-Python: >=3.6
Requires-Dist: numpy
